{
  "analyzeResult": {
    "modelVersion": "2022-04-30",
    "readResults": [
      {
        "angle": 2.6026,
        "height": 845,
        "lines": [
          {
            "appearance": {
              "style": {
                "confidence": 1,
                "name": "handwriting"
              }
            },
            "boundingBox": [
              79,
              172,
              101,
              173,
              100,
              193,
              78,
              192
            ],
            "text": "12",
            "words": [
              {
                "boundingBox": [
                  78,
                  172,
                  97,
                  173,
                  96,
                  193,
                  78,
                  192
                ],
                "confidence": 0.997,
                "text": "12"
              }
            ]
          },
          {
            "appearance": {
              "style": {
                "confidence": 1,
                "name": "handwriting"
              }
            },
            "boundingBox": [
              76,
              225,
              98,
              226,
              97,
              251,
              75,
              250
            ],
            "text": "13",
            "words": [
              {
                "boundingBox": [
                  76,
                  225,
                  96,
                  226,
                  95,
                  251,
                  75,
                  250
                ],
                "confidence": 0.988,
                "text": "13"
              }
            ]
          }
        ],
        "page": 1,
        "unit": "pixel",
        "width": 105
      }
    ],
    "version": "3.2.0"
  },
  "createdDateTime": "2024-09-30T22:10:35Z",
  "lastUpdatedDateTime": "2024-09-30T22:10:36Z",
  "status": "succeeded"
}